oidc_register/__init__.py
oidc_register/discovery.py
oidc_register/registration.py
oidc_register/registration_util.py
oidc_register-0.2.1.dist-info/LICENSE.txt
oidc_register-0.2.1.dist-info/METADATA
oidc_register-0.2.1.dist-info/WHEEL
oidc_register-0.2.1.dist-info/entry_points.txt
oidc_register-0.2.1.dist-info/top_level.txt
oidc_register-0.2.1.dist-info/RECORD
