Metadata-Version: 2.1
Name: oidc-register
Version: 0.2.1
Summary: OpenID Connect Dynamic Client Registration tool
Home-page: https://github.com/puiterwijk/oidc-register
Author: Patrick Uiterwijk
Author-email: patrick@puiterwijk.org
License: UNKNOWN
Platform: UNKNOWN
Classifier: License :: OSI Approved :: BSD License
Classifier: Operating System :: OS Independent
Classifier: Programming Language :: Python
Classifier: Programming Language :: Python :: 2
Classifier: Programming Language :: Python :: 2.6
Classifier: Programming Language :: Python :: 2.7
Classifier: Programming Language :: Python :: 3
Classifier: Programming Language :: Python :: 3.3
Classifier: Programming Language :: Python :: 3.4
License-File: LICENSE.txt
Requires-Dist: httplib2
